oceanum/eidos/README.md
oceanum/eidos/__init__.py
oceanum/eidos/_basemodel.py
oceanum/eidos/base.py
oceanum/eidos/common.py
oceanum/eidos/data.py
oceanum/eidos/exceptions.py
oceanum/eidos/features.py
oceanum/eidos/geojson.py
oceanum/eidos/oceanql.py
oceanum/eidos/panel.py
oceanum/eidos/root.py
oceanum/eidos/state.py
oceanum/eidos/theme.py
oceanum/eidos/vegaspec.py
oceanum/eidos/version.py
oceanum/eidos/_templates/__init__.py
oceanum/eidos/_templates/index.j2
oceanum/eidos/node/__init__.py
oceanum/eidos/node/document.py
oceanum/eidos/node/grid.py
oceanum/eidos/node/menu.py
oceanum/eidos/node/plot.py
oceanum/eidos/node/world.py
oceanum/eidos/node/worldlayer/__init__.py
oceanum/eidos/node/worldlayer/common.py
oceanum/eidos/node/worldlayer/feature.py
oceanum/eidos/node/worldlayer/gridded.py
oceanum/eidos/node/worldlayer/label.py
oceanum/eidos/node/worldlayer/scenegraph.py
oceanum/eidos/node/worldlayer/sea_surface.py
oceanum/eidos/node/worldlayer/seasurface.py
oceanum/eidos/node/worldlayer/track.py
oceanum/eidos/node/worldlayer/wmts.py
oceanum_eidos-0.9.0.dist-info/METADATA
oceanum_eidos-0.9.0.dist-info/WHEEL
oceanum_eidos-0.9.0.dist-info/top_level.txt
oceanum_eidos-0.9.0.dist-info/RECORD
