Metadata-Version: 2.4
Name: oceanum.eidos
Version: 0.9.0
Summary: Python bindings for the EIDOS framework. Create and edit EIDOS specs from python.
Author-email: "Oceanum.io" <support@oceanum.io>
License: MIT License
Project-URL: Homepage, https://oceanum.io
Classifier: Development Status :: 3 - Alpha
Classifier: Intended Audience :: Developers
Classifier: Programming Language :: Python
Classifier: Programming Language :: Python :: 3
Classifier: Programming Language :: Python :: 3.9
Classifier: Programming Language :: Python :: 3.10
Classifier: Programming Language :: Python :: 3.11
Classifier: Programming Language :: Python :: Implementation :: CPython
Requires-Python: >=3.9
Requires-Dist: oceanum
Requires-Dist: pydantic
Requires-Dist: pandas
Requires-Dist: geopandas
Requires-Dist: xarray
Requires-Dist: altair
Requires-Dist: jinja2
Requires-Dist: jsonpatch
Provides-Extra: test
Requires-Dist: pytest; extra == "test"
Requires-Dist: pytest-cov; extra == "test"
Requires-Dist: tox; extra == "test"
Provides-Extra: development
Requires-Dist: datamodel-code-generator; extra == "development"
Provides-Extra: doc
Requires-Dist: sphinx; extra == "doc"
